gerapy_selenium/__init__.py
gerapy_selenium/__version__.py
gerapy_selenium/downloadermiddlewares.py
gerapy_selenium/pretend.py
gerapy_selenium/request.py
gerapy_selenium/settings.py
gerapy_selenium-0.0.3.dist-info/METADATA
gerapy_selenium-0.0.3.dist-info/WHEEL
gerapy_selenium-0.0.3.dist-info/top_level.txt
gerapy_selenium-0.0.3.dist-info/RECORD
